aejuice_base_logger/__init__.py
aejuice_base_logger/aejuice_base_logger.py
aejuice_base_logger/aejuice_base_logger_test.py
aejuice_base_logger-1.0.0.dist-info/WHEEL
aejuice_base_logger-1.0.0.dist-info/METADATA
aejuice_base_logger-1.0.0.dist-info/RECORD
